{
  "version": "7",
  "dialect": "postgresql",
  "entries": [
    {
      "idx": 0,
      "version": "7",
      "when": 1782913635147,
      "tag": "0000_chemical_spencer_smythe",
      "breakpoints": true
    },
    {
      "idx": 1,
      "version": "7",
      "when": 1782982314078,
      "tag": "0001_redundant_nomad",
      "breakpoints": true
    },
    {
      "idx": 2,
      "version": "7",
      "when": 1783003556012,
      "tag": "0002_familiar_wither",
      "breakpoints": true
    }
  ]
}